mofdb_client/__init__.py
mofdb_client/adsorbate.py
mofdb_client/adsorbent.py
mofdb_client/element.py
mofdb_client/isotherm.py
mofdb_client/main.py
mofdb_client/mof.py
mofdb_client/temperature_point.py
mofdb_client_n8ta-0.0.2.dist-info/LICENSE
mofdb_client_n8ta-0.0.2.dist-info/METADATA
mofdb_client_n8ta-0.0.2.dist-info/WHEEL
mofdb_client_n8ta-0.0.2.dist-info/top_level.txt
mofdb_client_n8ta-0.0.2.dist-info/RECORD
