Metadata-Version: 2.1
Name: mofdb-client-n8ta
Version: 0.0.2
Summary: Simple client for fetching data from mofdb
Home-page: https://github.com/n8ta/mofdb-client
Author: Nathaniel Tracy-Amoroso
Author-email: n8@u.northwestern.edu
Maintainer: Nathaniel Tracy-Amoroso
Maintainer-email: n8@u.northwestern.edu
License: MIT License
Project-URL: MofDB, https://mof.tech.northwestern.edu
Keywords: mofdb,client,metal organic frameworks,chemistry
Platform: UNKNOWN
Classifier: Programming Language :: Python :: 3
Classifier: License :: OSI Approved :: MIT License
Classifier: Operating System :: OS Independent
License-File: LICENSE
